pysenseload/__init__.py
pysenseload/pysenseload.py
pysenseload-0.4.0.dist-info/WHEEL
pysenseload-0.4.0.dist-info/RECORD
pysenseload-0.4.0.dist-info/entry_points.txt
pysenseload-0.4.0.dist-info/METADATA
pysenseload-0.4.0.dist-info/DESCRIPTION.rst
pysenseload-0.4.0.dist-info/top_level.txt
pysenseload-0.4.0.dist-info/metadata.json
