Metadata-Version: 2.0
Name: pysenseload
Version: 0.4.0
Summary: Show system load on sense hat (RPi)
Home-page: https://github.com/oscarsix/pySenseLoad
Author: Oskar Malnowicz
Author-email: oscarsix@protonmail.ch
License: MIT
Keywords: sense hat,raspberrypi
Platform: UNKNOWN
Requires-Dist: sense-hat
Requires-Dist: Click
Requires-Dist: daemon
